qurane/__init__.py
qurane/quran.json
qurane/quran.py
qurane/search.py
qurane/tafser.json
qurane/tafser.py
TQuarnu-1.5.dist-info/METADATA
TQuarnu-1.5.dist-info/WHEEL
TQuarnu-1.5.dist-info/top_level.txt
TQuarnu-1.5.dist-info/RECORD
