Metadata-Version: 2.1
Name: TQuarnu
Version: 1.5
Summary: A modern and advanced Quran library for Arabic text and Tafsir
Home-page: 
Author: Khattab Aluqba
Author-email: 
License: MIT
Classifier: Programming Language :: Python :: 3
Classifier: License :: OSI Approved :: MIT License
Classifier: Operating System :: OS Independent
Requires-Python: >=3.7
